creates_psk/__init__.py
creates_psk/calculations.py
creates_psk-0.1.0.dist-info/METADATA
creates_psk-0.1.0.dist-info/WHEEL
creates_psk-0.1.0.dist-info/top_level.txt
creates_psk-0.1.0.dist-info/RECORD
