Metadata-Version: 2.1
Name: creates-psk
Version: 0.1.0
Summary: Datalakehouse development Project Starter Kit for Creates
Home-page: https://placeholder.io/
Author: Jessy Schurink
Author-email: j.schurink@creates.nl
License: MIT
Classifier: Intended Audience :: Developers
Classifier: License :: OSI Approved :: MIT License
Classifier: Programming Language :: Python
Classifier: Programming Language :: Python :: 3
Classifier: Programming Language :: Python :: 3.6
Classifier: Programming Language :: Python :: 3.7
Classifier: Programming Language :: Python :: 3.8
Classifier: Programming Language :: Python :: 3.9
Classifier: Operating System :: OS Independent
Requires-Dist: numpy
